[
  {
    "type": 1,
    "className": "/Script/FactoryGame.FGWorldSettings",
    "reference": {
      "levelName": "Persistent_Level",
      "pathName": "Persistent_Level:PersistentLevel.FGWorldSettings"
    },
    "needTransform": false,
    "transform": {
      "rotation": {
        "x": 0,
        "y": 0,
        "z": 0,
        "w": 1
      },
      "translation": {
        "x": 0,
        "y": 0,
        "z": 0
      },
      "scale": {
        "x": 1,
        "y": 1,
        "z": 1
      }
    },
    "wasPlacedInLevel": true,
    "pcInfo": {
      "parent": {
        "levelName": "",
        "pathName": ""
      },
      "children": []
    },
    "properties": {
      "mBuildableSubsystem": {
        "levelName": "Persistent_Level",
        "pathName": "Persistent_Level:PersistentLevel.BuildableSubsystem"
      }
    }
  }
]